README.md
setup.py
knock/__init__.py
knock/knock.py
knock.egg-info/PKG-INFO
knock.egg-info/SOURCES.txt
knock.egg-info/dependency_links.txt
knock.egg-info/entry_points.txt
knock.egg-info/top_level.txt