Metadata-Version: 1.0
Name: knock
Version: 0.0.1
Summary: Trinity's hack emulation into Neo's computer
Home-page: UNKNOWN
Author: BrainDisassembly
Author-email: braindisassm@gmail.com
License: GPL v3
Platform: UNKNOWN
